tanuki/__init__.py
tanuki/assertion_visitor.py
tanuki/bloom_filter.py
tanuki/constants.py
tanuki/function_modeler.py
tanuki/register.py
tanuki/repair.py
tanuki/utils.py
tanuki/validator.py
tanuki/language_models/__init__.py
tanuki/language_models/aws_bedrock_api.py
tanuki/language_models/embedding_api_abc.py
tanuki/language_models/embedding_model_manager.py
tanuki/language_models/language_model_manager.py
tanuki/language_models/llama_bedrock_api.py
tanuki/language_models/llm_api_abc.py
tanuki/language_models/llm_finetune_api_abc.py
tanuki/language_models/openai_api.py
tanuki/language_models/titan_bedrock_api.py
tanuki/language_models/togetherai_api.py
tanuki/language_models/llm_configs/__init__.py
tanuki/language_models/llm_configs/abc_base_config.py
tanuki/language_models/llm_configs/claude_config.py
tanuki/language_models/llm_configs/llama_config.py
tanuki/language_models/llm_configs/model_config_factory.py
tanuki/language_models/llm_configs/openai_config.py
tanuki/language_models/llm_configs/titan_config.py
tanuki/language_models/llm_configs/togetherai_config.py
tanuki/models/__init__.py
tanuki/models/api_manager.py
tanuki/models/embedding.py
tanuki/models/embedding_model_output.py
tanuki/models/finetune_job.py
tanuki/models/function_config.py
tanuki/models/function_description.py
tanuki/models/function_example.py
tanuki/models/function_type.py
tanuki/models/language_model_output.py
tanuki/persistence/__init__.py
tanuki/persistence/persistence_factory.py
tanuki/persistence/persistence_layer_interface.py
tanuki/persistence/filter/__init__.py
tanuki/persistence/filter/bloom_interface.py
tanuki/persistence/filter/filesystem_bloom.py
tanuki/trackers/__init__.py
tanuki/trackers/abc_buffered_logger.py
tanuki/trackers/dataset_worker.py
tanuki/trackers/filesystem_buffered_logger.py
tanuki.py-0.2.0.dist-info/LICENSE.txt
tanuki.py-0.2.0.dist-info/METADATA
tanuki.py-0.2.0.dist-info/WHEEL
tanuki.py-0.2.0.dist-info/top_level.txt
tanuki.py-0.2.0.dist-info/RECORD
