Metadata-Version: 2.1
Name: tanuki.py
Version: 0.2.0
Summary: The easiest way to build scalable LLM-powered applications, which gets cheaper and faster over time.
Home-page: https://github.com/Tanuki/tanuki.py
Download-URL: https://github.com/Tanuki/tanuki.py/archive/v0.1.0.tar.gz
Author: Jack Hopkins
Author-email: jack.hopkins@me.com
License: MIT
Keywords: python,ai,tdd,alignment,tanuki,distillation,pydantic,gpt-4,llm,chat-gpt,gpt-4-api,ai-functions
Classifier: Development Status :: 3 - Alpha
Classifier: Intended Audience :: Developers
Classifier: Topic :: Software Development :: Build Tools
Classifier: License :: OSI Approved :: MIT License
Classifier: Programming Language :: Python :: 3
Requires-Python: >=3.6
License-File: LICENSE.txt
Requires-Dist: appdirs ~=1.4.4
Requires-Dist: openai ==1.3.5
Requires-Dist: numpy >=1.17.3
Requires-Dist: python-dotenv ==1.0.0
Requires-Dist: bitarray ==2.8.2
Requires-Dist: pydantic >1.0.0
Requires-Dist: requests ~=2.31.0
Provides-Extra: aws_bedrock
Requires-Dist: boto3 ==1.33.1 ; extra == 'aws_bedrock'
Requires-Dist: botocore ==1.33.1 ; extra == 'aws_bedrock'
Provides-Extra: together_ai
Requires-Dist: together ==0.2.11 ; extra == 'together_ai'
